chem_kit/__init__.py
chem_kit/chem_doodle.py
chem_kit/molecule.py
chem_kit/transformation/__init__.py
chem_kit/transformation/generator.py
chem_kit/transformation/simplifier/__init__.py
chem_kit/transformation/simplifier/molecule_simplifier.py
chem_kit/transformation/simplifier/params.py
chem_kit/transformation/transformation.py
chem_kit-0.1.6.dist-info/LICENSE
chem_kit-0.1.6.dist-info/WHEEL
chem_kit-0.1.6.dist-info/METADATA
chem_kit-0.1.6.dist-info/RECORD
