Metadata-Version: 2.1
Name: chem-kit
Version: 0.1.6
Summary: A chemical toolbox based on RDKit
Home-page: https://gitlab.com/metwork/chem-kit
License: GPL-3.0-only
Author: Yann Beauxis
Author-email: dev@yannbeauxis.net
Requires-Python: >=3.7.1,<4.0.0
Classifier: License :: OSI Approved :: GNU General Public License v3 (GPLv3)
Classifier: Programming Language :: Python :: 3
Classifier: Programming Language :: Python :: 3.8
Classifier: Programming Language :: Python :: 3.9
Requires-Dist: Pillow (>=8.2.0,<9.0.0)
Requires-Dist: ipython (>=7.21.0,<8.0.0)
Requires-Dist: numpy (>=1.19.5,<2.0.0)
Requires-Dist: pandas (>=1.2.1,<2.0.0)
Requires-Dist: pydantic (>=1.8.1,<2.0.0)
Project-URL: Documentation, http://chem-kit.metwork.science
Project-URL: Repository, https://gitlab.com/metwork/chem-kit
